[
{"senado_membership_registration_id": "492", "start_date": "2019-02-01", "finish_data": "2023-01-31", "person_registration_id": "5573", "senador_name": "Abel Rebouças", "name": "Abel Rebouças São José", "role_resource_uri": "d69fcc38-21a6-41ee-8c0f-90be24aff805"},
{"senado_membership_registration_id": "487", "start_date": "2015-02-01", "finish_data": "2019-01-31", "person_registration_id": "5154", "senador_name": "Abiancy Cadoso Rosa", "name": "Abiancy Cadoso Rosa", "role_resource_uri": "d69fcc38-21a6-41ee-8c0f-90be24aff805"},
{"senado_membership_registration_id": "515", "start_date": "2019-02-01", "finish_data": "2023-01-31", "person_registration_id": "4981", "senador_name": "Acir Gurgacz", "name": "Acir Marcos Gurgacz", "role_resource_uri": "d69fcc38-21a6-41ee-8c0f-90be24aff805"},
{"senado_membership_registration_id": "497", "start_date": "2019-02-01", "finish_data": "2023-01-31", "person_registration_id": "5625", "senador_name": "Adilson Silva dos Santos", "name": "Adilson Silva dos Santos", "role_resource_uri": "d69fcc38-21a6-41ee-8c0f-90be24aff805"},
{"senado_membership_registration_id": "451", "start_date": "2015-02-01", "finish_data": "2019-01-31", "person_registration_id": "5170", "senador_name": "Agimiro Dias da Costa", "name": "Agimiro Dias da Costa", "role_resource_uri": "d69fcc38-21a6-41ee-8c0f-90be24aff805"},
{"senado_membership_registration_id": "485", "start_date": "2015-02-01", "finish_data": "2019-01-31", "person_registration_id": "5140", "senador_name": "Airton Sandoval", "name": "Airton Sandoval Santana", "role_resource_uri": "d69fcc38-21a6-41ee-8c0f-90be24aff805"},
{"senado_membership_registration_id": "495", "start_date": "2019-02-01", "finish_data": "2023-01-31", "person_registration_id": "4610", "senador_name": "Alexandre Silveira", "name": "Alexandre Silveira de Oliveira", "role_resource_uri": "d69fcc38-21a6-41ee-8c0f-90be24aff805"},
{"senado_membership_registration_id": "485", "start_date": "2015-02-01", "finish_data": "2019-01-31", "person_registration_id": "846", "senador_name": "Aloysio Nunes Ferreira", "name": "Aloysio Nunes Ferreira Filho", "role_resource_uri": "d69fcc38-21a6-41ee-8c0f-90be24aff805"},
{"senado_membership_registration_id": "514", "start_date": "2019-02-01", "finish_data": "2023-01-31", "person_registration_id": "945", "senador_name": "Alvaro Dias", "name": "Alvaro Fernandes Dias", "role_resource_uri": "d69fcc38-21a6-41ee-8c0f-90be24aff805"},
{"senado_membership_registration_id": "496", "start_date": "2019-02-01", "finish_data": "2023-01-31", "person_registration_id": "5607", "senador_name": "Alzenir Porto", "name": "Maria Alzenir Porto da Costa", "role_resource_uri": "d69fcc38-21a6-41ee-8c0f-90be24aff805"},
{"senado_membership_registration_id": "437", "start_date": "2015-02-01", "finish_data": "2019-01-31", "person_registration_id": "5042", "senador_name": "Alzira Ferreira Barros", "name": "Alzira Ferreira Barros", "role_resource_uri": "d69fcc38-21a6-41ee-8c0f-90be24aff805"},
{"senado_membership_registration_id": "462", "start_date": "2015-02-01", "finish_data": "2019-01-31", "person_registration_id": "4988", "senador_name": "Ana Amélia", "name": "Ana Amélia de Lemos", "role_resource_uri": "d69fcc38-21a6-41ee-8c0f-90be24aff805"},
{"senado_membership_registration_id": "475", "start_date": "2015-02-01", "finish_data": "2019-01-31", "person_registration_id": "5046", "senador_name": "Andrelina Barbosa da Cunha", "name": "Andrelina Barbosa da Cunha", "role_resource_uri": "d69fcc38-21a6-41ee-8c0f-90be24aff805"},
{"senado_membership_registration_id": "495", "start_date": "2019-02-01", "finish_data": "2023-01-31", "person_registration_id": "5529", "senador_name": "Antonio Anastasia", "name": "Antonio Augusto Junho Anastasia", "role_resource_uri": "d69fcc38-21a6-41ee-8c0f-90be24aff805"},
{"senado_membership_registration_id": "471", "start_date": "2015-02-01", "finish_data": "2019-01-31", "person_registration_id": "5150", "senador_name": "Antonio Carlos Rodrigues", "name": "Antonio Carlos Rodrigues", "role_resource_uri": "d69fcc38-21a6-41ee-8c0f-90be24aff805"},
{"senado_membership_registration_id": "474", "start_date": "2015-02-01", "finish_data": "2019-01-31", "person_registration_id": "3", "senador_name": "Antonio Carlos Valadares", "name": "Antonio Carlos Valadares", "role_resource_uri": "d69fcc38-21a6-41ee-8c0f-90be24aff805"},
{"senado_membership_registration_id": "465", "start_date": "2015-02-01", "finish_data": "2019-01-31", "person_registration_id": "5134", "senador_name": "Antônio Marcos Gavazzoni", "name": "Antônio Marcos Gavazzoni", "role_resource_uri": "d69fcc38-21a6-41ee-8c0f-90be24aff805"},
{"senado_membership_registration_id": "457", "start_date": "2015-02-01", "finish_data": "2019-01-31", "person_registration_id": "5032", "senador_name": "Antônio Milton Pessoa Falcão Filho", "name": "Antônio Milton Pessoa Falcão Filho", "role_resource_uri": "d69fcc38-21a6-41ee-8c0f-90be24aff805"},
{"senado_membership_registration_id": "440", "start_date": "2015-02-01", "finish_data": "2019-01-31", "person_registration_id": "5168", "senador_name": "Aristavora de Souza Santos", "name": "Aristavora de Souza Santos", "role_resource_uri": "d69fcc38-21a6-41ee-8c0f-90be24aff805"},
{"senado_membership_registration_id": "442", "start_date": "2015-02-01", "finish_data": "2019-01-31", "person_registration_id": "5028", "senador_name": "Armando José de Oliveira", "name": "Armando José de Oliveira", "role_resource_uri": "d69fcc38-21a6-41ee-8c0f-90be24aff805"},
{"senado_membership_registration_id": "443", "start_date": "2015-02-01", "finish_data": "2019-01-31", "person_registration_id": "715", "senador_name": "Armando Monteiro", "name": "Armando de Queiroz Monteiro Neto", "role_resource_uri": "d69fcc38-21a6-41ee-8c0f-90be24aff805"},
{"senado_membership_registration_id": "468", "start_date": "2015-02-01", "finish_data": "2019-01-31", "person_registration_id": "5164", "senador_name": "Ataídes Oliveira", "name": "Ataídes de Oliveira", "role_resource_uri": "d69fcc38-21a6-41ee-8c0f-90be24aff805"},
{"senado_membership_registration_id": "466", "start_date": "2015-02-01", "finish_data": "2019-01-31", "person_registration_id": "5138", "senador_name": "Athos de Almeida Lopes", "name": "Athos de Almeida Lopes", "role_resource_uri": "d69fcc38-21a6-41ee-8c0f-90be24aff805"},
{"senado_membership_registration_id": "516", "start_date": "2019-02-01", "finish_data": "2023-01-31", "person_registration_id": "5633", "senador_name": "Atilio Francisco", "name": "Atilio Francisco da Silva", "role_resource_uri": "d69fcc38-21a6-41ee-8c0f-90be24aff805"},
{"senado_membership_registration_id": "499", "start_date": "2019-02-01", "finish_data": "2023-01-31", "person_registration_id": "5631", "senador_name": "Ayres Marchetti", "name": "Genésio Ayres Marchetti", "role_resource_uri": "d69fcc38-21a6-41ee-8c0f-90be24aff805"},
{"senado_membership_registration_id": "435", "start_date": "2015-02-01", "finish_data": "2019-01-31", "person_registration_id": "391", "senador_name": "Aécio Neves", "name": "Aécio Neves da Cunha", "role_resource_uri": "d69fcc38-21a6-41ee-8c0f-90be24aff805"},
{"senado_membership_registration_id": "457", "start_date": "2015-02-01", "finish_data": "2019-01-31", "person_registration_id": "3823", "senador_name": "Benedito de Lira", "name": "Benedito de Lira", "role_resource_uri": "d69fcc38-21a6-41ee-8c0f-90be24aff805"},
{"senado_membership_registration_id": "518", "start_date": "2019-02-01", "finish_data": "2023-01-31", "person_registration_id": "5639", "senador_name": "Bispo Guaracy", "name": "Guaracy Batista da Silveira", "role_resource_uri": "d69fcc38-21a6-41ee-8c0f-90be24aff805"},
{"senado_membership_registration_id": "500", "start_date": "2019-02-01", "finish_data": "2023-01-31", "person_registration_id": "5559", "senador_name": "Bispo José", "name": "José Afonso Teixeira", "role_resource_uri": "d69fcc38-21a6-41ee-8c0f-90be24aff805"},
{"senado_membership_registration_id": "456", "start_date": "2015-02-01", "finish_data": "2019-01-31", "person_registration_id": "111", "senador_name": "Blairo Maggi", "name": "Blairo Borges Maggi", "role_resource_uri": "d69fcc38-21a6-41ee-8c0f-90be24aff805"},
{"senado_membership_registration_id": "519", "start_date": "2019-02-01", "finish_data": "2023-01-31", "person_registration_id": "5603", "senador_name": "Carlos Augusto Costa", "name": "Carlos Augusto Lopes da Costa", "role_resource_uri": "d69fcc38-21a6-41ee-8c0f-90be24aff805"},
{"senado_membership_registration_id": "494", "start_date": "2019-02-01", "finish_data": "2023-01-31", "person_registration_id": "5593", "senador_name": "Celso Dal Lago Rodrigues", "name": "Celso Dal Lago Rodrigues", "role_resource_uri": "d69fcc38-21a6-41ee-8c0f-90be24aff805"},
{"senado_membership_registration_id": "466", "start_date": "2015-02-01", "finish_data": "2019-01-31", "person_registration_id": "5136", "senador_name": "Cesar Antonio de Souza", "name": "Cesar Antonio de Souza", "role_resource_uri": "d69fcc38-21a6-41ee-8c0f-90be24aff805"},
{"senado_membership_registration_id": "512", "start_date": "2019-02-01", "finish_data": "2023-01-31", "person_registration_id": "611", "senador_name": "Chiquinho Feitosa", "name": "Francisco Feitosa de Albuquerque Lima", "role_resource_uri": "d69fcc38-21a6-41ee-8c0f-90be24aff805"},
{"senado_membership_registration_id": "497", "start_date": "2019-02-01", "finish_data": "2023-01-31", "person_registration_id": "5623", "senador_name": "Christopher Goulart", "name": "Christopher Belchior Goulart", "role_resource_uri": "d69fcc38-21a6-41ee-8c0f-90be24aff805"},
{"senado_membership_registration_id": "456", "start_date": "2015-02-01", "finish_data": "2019-01-31", "person_registration_id": "5108", "senador_name": "Cidinho Santos", "name": "José Aparecido dos Santos", "role_resource_uri": "d69fcc38-21a6-41ee-8c0f-90be24aff805"},
{"senado_membership_registration_id": "458", "start_date": "2015-02-01", "finish_data": "2019-01-31", "person_registration_id": "739", "senador_name": "Ciro Nogueira", "name": "Ciro Nogueira Lima Filho", "role_resource_uri": "d69fcc38-21a6-41ee-8c0f-90be24aff805"},
{"senado_membership_registration_id": "438", "start_date": "2015-02-01", "finish_data": "2019-01-31", "person_registration_id": "3881", "senador_name": "Clovis Fecury", "name": "Clovis Antônio Chaves Fecury", "role_resource_uri": "d69fcc38-21a6-41ee-8c0f-90be24aff805"},
{"senado_membership_registration_id": "475", "start_date": "2015-02-01", "finish_data": "2019-01-31", "person_registration_id": "5044", "senador_name": "Clécio Luis Vilhena Vieira", "name": "Clécio Luis Vilhena Vieira", "role_resource_uri": "d69fcc38-21a6-41ee-8c0f-90be24aff805"},
{"senado_membership_registration_id": "452", "start_date": "2015-02-01", "finish_data": "2019-01-31", "person_registration_id": "3398", "senador_name": "Cristovam Buarque", "name": "Cristovam Ricardo Cavalcanti Buarque", "role_resource_uri": "d69fcc38-21a6-41ee-8c0f-90be24aff805"},
{"senado_membership_registration_id": "489", "start_date": "2015-02-01", "finish_data": "2019-01-31", "person_registration_id": "1757", "senador_name": "Cunha Lima", "name": "Ivandro Moura Cunha Lima", "role_resource_uri": "d69fcc38-21a6-41ee-8c0f-90be24aff805"},
{"senado_membership_registration_id": "489", "start_date": "2015-02-01", "finish_data": "2019-01-31", "person_registration_id": "5197", "senador_name": "Cássio Cunha Lima", "name": "Cássio Rodrigues da Cunha Lima", "role_resource_uri": "d69fcc38-21a6-41ee-8c0f-90be24aff805"},
{"senado_membership_registration_id": "465", "start_date": "2015-02-01", "finish_data": "2019-01-31", "person_registration_id": "5132", "senador_name": "Dalirio Beber", "name": "Dalírio José Beber", "role_resource_uri": "d69fcc38-21a6-41ee-8c0f-90be24aff805"},
{"senado_membership_registration_id": "501", "start_date": "2019-02-01", "finish_data": "2023-01-31", "person_registration_id": "3830", "senador_name": "Davi Alcolumbre", "name": "David Samuel Alcolumbre Tobelem", "role_resource_uri": "d69fcc38-21a6-41ee-8c0f-90be24aff805"},
{"senado_membership_registration_id": "489", "start_date": "2015-02-01", "finish_data": "2019-01-31", "person_registration_id": "5199", "senador_name": "Deca", "name": "José Gonzaga Sobrinho", "role_resource_uri": "d69fcc38-21a6-41ee-8c0f-90be24aff805"},
{"senado_membership_registration_id": "447", "start_date": "2015-02-01", "finish_data": "2019-01-31", "person_registration_id": "3360", "senador_name": "Delcídio do Amaral", "name": "Delcídio do Amaral Gomez", "role_resource_uri": "d69fcc38-21a6-41ee-8c0f-90be24aff805"},
{"senado_membership_registration_id": "472", "start_date": "2015-02-01", "finish_data": "2019-01-31", "person_registration_id": "3399", "senador_name": "Demóstenes Torres", "name": "Demóstenes Lazaro Xavier Torres", "role_resource_uri": "d69fcc38-21a6-41ee-8c0f-90be24aff805"},
{"senado_membership_registration_id": "518", "start_date": "2019-02-01", "finish_data": "2023-01-31", "person_registration_id": "5637", "senador_name": "Donizeti Nogueira", "name": "Divino Donizeti Borges Nogueira", "role_resource_uri": "d69fcc38-21a6-41ee-8c0f-90be24aff805"},
{"senado_membership_registration_id": "443", "start_date": "2015-02-01", "finish_data": "2019-01-31", "person_registration_id": "5178", "senador_name": "Douglas Cintra", "name": "Douglas Mauricio Ramos Cintra", "role_resource_uri": "d69fcc38-21a6-41ee-8c0f-90be24aff805"},
{"senado_membership_registration_id": "493", "start_date": "2019-02-01", "finish_data": "2023-01-31", "person_registration_id": "5565", "senador_name": "Dr. Helder Cavalcante", "name": "Francisco Helder Cavalcante Sousa", "role_resource_uri": "d69fcc38-21a6-41ee-8c0f-90be24aff805"},
{"senado_membership_registration_id": "511", "start_date": "2019-02-01", "finish_data": "2023-01-31", "person_registration_id": "5561", "senador_name": "Drª Renilde", "name": "Renilde Silva Bulhões Barros", "role_resource_uri": "d69fcc38-21a6-41ee-8c0f-90be24aff805"},
{"senado_membership_registration_id": "499", "start_date": "2019-02-01", "finish_data": "2023-01-31", "person_registration_id": "5537", "senador_name": "Dário Berger", "name": "Dário Elias Berger", "role_resource_uri": "d69fcc38-21a6-41ee-8c0f-90be24aff805"},
{"senado_membership_registration_id": "445", "start_date": "2015-02-01", "finish_data": "2019-01-31", "person_registration_id": "16", "senador_name": "Edison Lobão", "name": "Edison Lobão", "role_resource_uri": "d69fcc38-21a6-41ee-8c0f-90be24aff805"},
{"senado_membership_registration_id": "482", "start_date": "2015-02-01", "finish_data": "2019-01-31", "person_registration_id": "5160", "senador_name": "Edivaldo Edilson Pantoja da Silva", "name": "Edivaldo Edilson Pantoja da Silva", "role_resource_uri": "d69fcc38-21a6-41ee-8c0f-90be24aff805"},
{"senado_membership_registration_id": "478", "start_date": "2015-02-01", "finish_data": "2019-01-31", "person_registration_id": "4721", "senador_name": "Eduardo Amorim", "name": "Eduardo Alves do Amorim", "role_resource_uri": "d69fcc38-21a6-41ee-8c0f-90be24aff805"},
{"senado_membership_registration_id": "473", "start_date": "2015-02-01", "finish_data": "2019-01-31", "person_registration_id": "4994", "senador_name": "Eduardo Braga", "name": "Carlos Eduardo de Souza Braga", "role_resource_uri": "d69fcc38-21a6-41ee-8c0f-90be24aff805"},
{"senado_membership_registration_id": "480", "start_date": "2015-02-01", "finish_data": "2019-01-31", "person_registration_id": "4767", "senador_name": "Eduardo Lopes", "name": "Eduardo Benedito Lopes", "role_resource_uri": "d69fcc38-21a6-41ee-8c0f-90be24aff805"},
{"senado_membership_registration_id": "504", "start_date": "2019-02-01", "finish_data": "2023-01-31", "person_registration_id": "5587", "senador_name": "Eladio Carneiro", "name": "Eladio Barbosa Carneiro", "role_resource_uri": "d69fcc38-21a6-41ee-8c0f-90be24aff805"},
{"senado_membership_registration_id": "441", "start_date": "2015-02-01", "finish_data": "2019-01-31", "person_registration_id": "5146", "senador_name": "Elaine Matozinhos Ribeiro", "name": "Elaine Matozinhos Ribeiro", "role_resource_uri": "d69fcc38-21a6-41ee-8c0f-90be24aff805"},
{"senado_membership_registration_id": "474", "start_date": "2015-02-01", "finish_data": "2019-01-31", "person_registration_id": "4969", "senador_name": "Elber Batalha", "name": "Elber Batalha de Goes", "role_resource_uri": "d69fcc38-21a6-41ee-8c0f-90be24aff805"},
{"senado_membership_registration_id": "519", "start_date": "2019-02-01", "finish_data": "2023-01-31", "person_registration_id": "5605", "senador_name": "Eliane Rodrigues", "name": "Eliane Rodrigues de Andrade Ferreira", "role_resource_uri": "d69fcc38-21a6-41ee-8c0f-90be24aff805"},
{"senado_membership_registration_id": "496", "start_date": "2019-02-01", "finish_data": "2023-01-31", "person_registration_id": "5531", "senador_name": "Elmano Férrer", "name": "Elmano Férrer de Almeida", "role_resource_uri": "d69fcc38-21a6-41ee-8c0f-90be24aff805"},
{"senado_membership_registration_id": "435", "start_date": "2015-02-01", "finish_data": "2019-01-31", "person_registration_id": "5148", "senador_name": "Elmiro Alves do Nascimento", "name": "Elmiro Alves do Nascimento", "role_resource_uri": "d69fcc38-21a6-41ee-8c0f-90be24aff805"},
{"senado_membership_registration_id": "436", "start_date": "2015-02-01", "finish_data": "2019-01-31", "person_registration_id": "5064", "senador_name": "Emir Simão Sader", "name": "Emir Simão Sader", "role_resource_uri": "d69fcc38-21a6-41ee-8c0f-90be24aff805"},
{"senado_membership_registration_id": "483", "start_date": "2015-02-01", "finish_data": "2019-01-31", "person_registration_id": "5126", "senador_name": "Enivaldo Euzébio dos Anjos", "name": "Enivaldo Euzébio dos Anjos", "role_resource_uri": "d69fcc38-21a6-41ee-8c0f-90be24aff805"},
{"senado_membership_registration_id": "450", "start_date": "2015-02-01", "finish_data": "2019-01-31", "person_registration_id": "612", "senador_name": "Eunício Oliveira", "name": "Eunício Lopes de Oliveira", "role_resource_uri": "d69fcc38-21a6-41ee-8c0f-90be24aff805"},
{"senado_membership_registration_id": "502", "start_date": "2019-02-01", "finish_data": "2023-01-31", "person_registration_id": "5581", "senador_name": "Fadi Faraj", "name": "Fadi Fayez Faraj", "role_resource_uri": "d69fcc38-21a6-41ee-8c0f-90be24aff805"},
{"senado_membership_registration_id": "519", "start_date": "2019-02-01", "finish_data": "2023-01-31", "person_registration_id": "5540", "senador_name": "Fernando Bezerra Coelho", "name": "Fernando Bezerra de Souza Coelho", "role_resource_uri": "d69fcc38-21a6-41ee-8c0f-90be24aff805"},
{"senado_membership_registration_id": "442", "start_date": "2015-02-01", "finish_data": "2019-01-31", "person_registration_id": "5026", "senador_name": "Fernando Carvalho Lage", "name": "Fernando Carvalho Lage", "role_resource_uri": "d69fcc38-21a6-41ee-8c0f-90be24aff805"},
{"senado_membership_registration_id": "511", "start_date": "2019-02-01", "finish_data": "2023-01-31", "person_registration_id": "4525", "senador_name": "Fernando Collor", "name": "Fernando Affonso Collor de Mello", "role_resource_uri": "d69fcc38-21a6-41ee-8c0f-90be24aff805"},
{"senado_membership_registration_id": "512", "start_date": "2019-02-01", "finish_data": "2023-01-31", "person_registration_id": "5577", "senador_name": "Fernando Façanha", "name": "Fernando Antonio Mendes Façanha Filho", "role_resource_uri": "d69fcc38-21a6-41ee-8c0f-90be24aff805"},
{"senado_membership_registration_id": "491", "start_date": "2015-02-01", "finish_data": "2019-01-31", "person_registration_id": "2632", "senador_name": "Fernando Ribeiro", "name": "Fernando de Castro Ribeiro", "role_resource_uri": "d69fcc38-21a6-41ee-8c0f-90be24aff805"},
{"senado_membership_registration_id": "472", "start_date": "2015-02-01", "finish_data": "2019-01-31", "person_registration_id": "4873", "senador_name": "Fleury", "name": "José Eduardo Fleury Fernandes Costa", "role_resource_uri": "d69fcc38-21a6-41ee-8c0f-90be24aff805"},
{"senado_membership_registration_id": "487", "start_date": "2015-02-01", "finish_data": "2019-01-31", "person_registration_id": "3634", "senador_name": "Flexa Ribeiro", "name": "Fernando de Souza Flexa Ribeiro", "role_resource_uri": "d69fcc38-21a6-41ee-8c0f-90be24aff805"},
{"senado_membership_registration_id": "437", "start_date": "2015-02-01", "finish_data": "2019-01-31", "person_registration_id": "553", "senador_name": "Francisco Garcia", "name": "Francisco Garcia Rodrigues", "role_resource_uri": "d69fcc38-21a6-41ee-8c0f-90be24aff805"},
{"senado_membership_registration_id": "467", "start_date": "2015-02-01", "finish_data": "2019-01-31", "person_registration_id": "5054", "senador_name": "Francisco Simeão Rodrigues Neto", "name": "Francisco Simeão Rodrigues Neto", "role_resource_uri": "d69fcc38-21a6-41ee-8c0f-90be24aff805"},
{"senado_membership_registration_id": "491", "start_date": "2015-02-01", "finish_data": "2019-01-31", "person_registration_id": "5416", "senador_name": "Francisco Wilson Ribeiro", "name": "Francisco Wilson Ribeiro", "role_resource_uri": "d69fcc38-21a6-41ee-8c0f-90be24aff805"},
{"senado_membership_registration_id": "469", "start_date": "2015-02-01", "finish_data": "2019-01-31", "person_registration_id": "5034", "senador_name": "Fábio Luiz Araújo Lopes de Farias", "name": "Fábio Luiz Araújo Lopes de Farias", "role_resource_uri": "d69fcc38-21a6-41ee-8c0f-90be24aff805"},
{"senado_membership_registration_id": "510", "start_date": "2019-02-01", "finish_data": "2023-01-31", "person_registration_id": "3713", "senador_name": "Fátima Bezerra", "name": "Maria de Fátima Bezerra", "role_resource_uri": "d69fcc38-21a6-41ee-8c0f-90be24aff805"},
{"senado_membership_registration_id": "482", "start_date": "2015-02-01", "finish_data": "2019-01-31", "person_registration_id": "5162", "senador_name": "Félix Urano Gama de Souza", "name": "Félix Urano Gama de Souza", "role_resource_uri": "d69fcc38-21a6-41ee-8c0f-90be24aff805"},
{"senado_membership_registration_id": "484", "start_date": "2015-02-01", "finish_data": "2019-01-31", "person_registration_id": "5024", "senador_name": "Gabriel Maia Gelpke", "name": "Gabriel Maia Gelpke", "role_resource_uri": "d69fcc38-21a6-41ee-8c0f-90be24aff805"},
{"senado_membership_registration_id": "476", "start_date": "2015-02-01", "finish_data": "2019-01-31", "person_registration_id": "87", "senador_name": "Garibaldi Alves Filho", "name": "Garibaldi Alves Filho", "role_resource_uri": "d69fcc38-21a6-41ee-8c0f-90be24aff805"},
{"senado_membership_registration_id": "464", "start_date": "2015-02-01", "finish_data": "2019-01-31", "person_registration_id": "4522", "senador_name": "Geovani Borges", "name": "Geovani Pinheiro Borges", "role_resource_uri": "d69fcc38-21a6-41ee-8c0f-90be24aff805"},
{"senado_membership_registration_id": "449", "start_date": "2015-02-01", "finish_data": "2019-01-31", "person_registration_id": "5088", "senador_name": "Gilberto Corazza", "name": "Gilberto Corazza", "role_resource_uri": "d69fcc38-21a6-41ee-8c0f-90be24aff805"},
{"senado_membership_registration_id": "515", "start_date": "2019-02-01", "finish_data": "2023-01-31", "person_registration_id": "5615", "senador_name": "Gilberto Piselo", "name": "Gilberto Piselo do Nascimento", "role_resource_uri": "d69fcc38-21a6-41ee-8c0f-90be24aff805"},
{"senado_membership_registration_id": "464", "start_date": "2015-02-01", "finish_data": "2019-01-31", "person_registration_id": "30", "senador_name": "Gilvam Borges", "name": "Gilvam Pinheiro Borges", "role_resource_uri": "d69fcc38-21a6-41ee-8c0f-90be24aff805"},
{"senado_membership_registration_id": "446", "start_date": "2015-02-01", "finish_data": "2019-01-31", "person_registration_id": "5128", "senador_name": "Gino Jose Ferreira", "name": "Gino Jose Ferreira", "role_resource_uri": "d69fcc38-21a6-41ee-8c0f-90be24aff805"},
{"senado_membership_registration_id": "500", "start_date": "2019-02-01", "finish_data": "2023-01-31", "person_registration_id": "4558", "senador_name": "Gladson Cameli", "name": "Gladson de Lima Cameli", "role_resource_uri": "d69fcc38-21a6-41ee-8c0f-90be24aff805"},
{"senado_membership_registration_id": "439", "start_date": "2015-02-01", "finish_data": "2019-01-31", "person_registration_id": "5006", "senador_name": "Gleisi Hoffmann", "name": "Gleisi Helena Hoffmann", "role_resource_uri": "d69fcc38-21a6-41ee-8c0f-90be24aff805"},
{"senado_membership_registration_id": "448", "start_date": "2015-02-01", "finish_data": "2019-01-31", "person_registration_id": "5008", "senador_name": "Humberto Costa", "name": "Humberto Sérgio Costa Lima", "role_resource_uri": "d69fcc38-21a6-41ee-8c0f-90be24aff805"},
{"senado_membership_registration_id": "470", "start_date": "2015-02-01", "finish_data": "2019-01-31", "person_registration_id": "5100", "senador_name": "Hélio José", "name": "Hélio José da Silva Lima", "role_resource_uri": "d69fcc38-21a6-41ee-8c0f-90be24aff805"},
{"senado_membership_registration_id": "459", "start_date": "2015-02-01", "finish_data": "2019-01-31", "person_registration_id": "5076", "senador_name": "Ione Borges Ribeiro Guimarães", "name": "Ione Borges Ribeiro Guimarães", "role_resource_uri": "d69fcc38-21a6-41ee-8c0f-90be24aff805"},
{"senado_membership_registration_id": "441", "start_date": "2015-02-01", "finish_data": "2019-01-31", "person_registration_id": "1754", "senador_name": "Itamar Franco", "name": "Itamar Augusto Cautiero Franco", "role_resource_uri": "d69fcc38-21a6-41ee-8c0f-90be24aff805"},
{"senado_membership_registration_id": "490", "start_date": "2015-02-01", "finish_data": "2019-01-31", "person_registration_id": "5418", "senador_name": "Ivanci Magno", "name": "Ivanci Magno", "role_resource_uri": "d69fcc38-21a6-41ee-8c0f-90be24aff805"},
{"senado_membership_registration_id": "477", "start_date": "2015-02-01", "finish_data": "2019-01-31", "person_registration_id": "5004", "senador_name": "Ivo Cassol", "name": "Ivo Narciso Cassol", "role_resource_uri": "d69fcc38-21a6-41ee-8c0f-90be24aff805"},
{"senado_membership_registration_id": "491", "start_date": "2015-02-01", "finish_data": "2019-01-31", "person_registration_id": "35", "senador_name": "Jader Barbalho", "name": "Jader Fontenelle Barbalho", "role_resource_uri": "d69fcc38-21a6-41ee-8c0f-90be24aff805"},
{"senado_membership_registration_id": "476", "start_date": "2015-02-01", "finish_data": "2019-01-31", "person_registration_id": "5022", "senador_name": "Janduhy Max Freire de Andrade", "name": "Janduhy Max Freire de Andrade", "role_resource_uri": "d69fcc38-21a6-41ee-8c0f-90be24aff805"},
{"senado_membership_registration_id": "510", "start_date": "2019-02-01", "finish_data": "2023-01-31", "person_registration_id": "5627", "senador_name": "Jean-Paul Prates", "name": "Jean-Paul Terra Prates", "role_resource_uri": "d69fcc38-21a6-41ee-8c0f-90be24aff805"},
{"senado_membership_registration_id": "448", "start_date": "2015-02-01", "finish_data": "2019-01-31", "person_registration_id": "724", "senador_name": "Joaquim Francisco", "name": "Joaquim Francisco de Freitas Cavalcanti", "role_resource_uri": "d69fcc38-21a6-41ee-8c0f-90be24aff805"},
{"senado_membership_registration_id": "514", "start_date": "2019-02-01", "finish_data": "2023-01-31", "person_registration_id": "5609", "senador_name": "Joel Malucelli", "name": "Joel Malucelli", "role_resource_uri": "d69fcc38-21a6-41ee-8c0f-90be24aff805"},
{"senado_membership_registration_id": "484", "start_date": "2015-02-01", "finish_data": "2019-01-31", "person_registration_id": "4990", "senador_name": "Jorge Viana", "name": "Jorge Ney Viana Macedo Neves", "role_resource_uri": "d69fcc38-21a6-41ee-8c0f-90be24aff805"},
{"senado_membership_registration_id": "506", "start_date": "2019-02-01", "finish_data": "2023-01-31", "person_registration_id": "4885", "senador_name": "Jorge Yanai", "name": "Jorge Yoshiaki Yanai", "role_resource_uri": "d69fcc38-21a6-41ee-8c0f-90be24aff805"},
{"senado_membership_registration_id": "496", "start_date": "2019-02-01", "finish_data": "2023-01-31", "person_registration_id": "5849", "name": "Jose Amauri P. de Araújo", "role_resource_uri": "d69fcc38-21a6-41ee-8c0f-90be24aff805"},
{"senado_membership_registration_id": "486", "start_date": "2015-02-01", "finish_data": "2019-01-31", "person_registration_id": "5078", "senador_name": "Jose Nagib da Silva Lima", "name": "Jose Nagib da Silva Lima", "role_resource_uri": "d69fcc38-21a6-41ee-8c0f-90be24aff805"},
{"senado_membership_registration_id": "501", "start_date": "2019-02-01", "finish_data": "2023-01-31", "person_registration_id": "5569", "senador_name": "Josiel", "name": "Jose Samuel Alcolumbre Tobelem", "role_resource_uri": "d69fcc38-21a6-41ee-8c0f-90be24aff805"},
{"senado_membership_registration_id": "481", "start_date": "2015-02-01", "finish_data": "2019-01-31", "person_registration_id": "40", "senador_name": "José Agripino", "name": "José Agripino Maia", "role_resource_uri": "d69fcc38-21a6-41ee-8c0f-90be24aff805"},
{"senado_membership_registration_id": "462", "start_date": "2015-02-01", "finish_data": "2019-01-31", "person_registration_id": "5090", "senador_name": "José Alberto Wenzel", "name": "José Alberto Wenzel", "role_resource_uri": "d69fcc38-21a6-41ee-8c0f-90be24aff805"},
{"senado_membership_registration_id": "458", "start_date": "2015-02-01", "finish_data": "2019-01-31", "person_registration_id": "5188", "senador_name": "José Amauri", "name": "José Amauri Pereira de Araújo", "role_resource_uri": "d69fcc38-21a6-41ee-8c0f-90be24aff805"},
{"senado_membership_registration_id": "455", "start_date": "2015-02-01", "finish_data": "2019-01-31", "person_registration_id": "5120", "senador_name": "José Antonio Guidoni", "name": "José Antonio Guidoni", "role_resource_uri": "d69fcc38-21a6-41ee-8c0f-90be24aff805"},
{"senado_membership_registration_id": "516", "start_date": "2019-02-01", "finish_data": "2023-01-31", "person_registration_id": "878", "senador_name": "José Aníbal", "name": "José Aníbal Peres de Pontes", "role_resource_uri": "d69fcc38-21a6-41ee-8c0f-90be24aff805"},
{"senado_membership_registration_id": "502", "start_date": "2019-02-01", "finish_data": "2023-01-31", "person_registration_id": "5579", "senador_name": "José Carlos Vasconcellos", "name": "José Carlos de Moraes Vasconcellos Filho", "role_resource_uri": "d69fcc38-21a6-41ee-8c0f-90be24aff805"},
{"senado_membership_registration_id": "474", "start_date": "2015-02-01", "finish_data": "2019-01-31", "person_registration_id": "43", "senador_name": "José Eduardo Dutra", "name": "José Eduardo de Barros Dutra", "role_resource_uri": "d69fcc38-21a6-41ee-8c0f-90be24aff805"},
{"senado_membership_registration_id": "457", "start_date": "2015-02-01", "finish_data": "2019-01-31", "person_registration_id": "5030", "senador_name": "José Givago Raposo Tenório", "name": "José Givago Raposo Tenório", "role_resource_uri": "d69fcc38-21a6-41ee-8c0f-90be24aff805"},
{"senado_membership_registration_id": "513", "start_date": "2019-02-01", "finish_data": "2023-01-31", "person_registration_id": "3361", "senador_name": "José Maranhão", "name": "José Targino Maranhão", "role_resource_uri": "d69fcc38-21a6-41ee-8c0f-90be24aff805"},
{"senado_membership_registration_id": "463", "start_date": "2015-02-01", "finish_data": "2019-01-31", "person_registration_id": "5112", "senador_name": "José Medeiros", "name": "José Antônio Medeiros", "role_resource_uri": "d69fcc38-21a6-41ee-8c0f-90be24aff805"},
{"senado_membership_registration_id": "444", "start_date": "2015-02-01", "finish_data": "2019-01-31", "person_registration_id": "615", "senador_name": "José Pimentel", "name": "José Barroso Pimentel", "role_resource_uri": "d69fcc38-21a6-41ee-8c0f-90be24aff805"},
{"senado_membership_registration_id": "488", "start_date": "2015-02-01", "finish_data": "2019-01-31", "person_registration_id": "5184", "senador_name": "José Ribamar Noleto de Santana", "name": "José Ribamar Noleto de Santana", "role_resource_uri": "d69fcc38-21a6-41ee-8c0f-90be24aff805"},
{"senado_membership_registration_id": "443", "start_date": "2015-02-01", "finish_data": "2019-01-31", "person_registration_id": "5180", "senador_name": "José Rodrigues da Silva", "name": "José Rodrigues da Silva", "role_resource_uri": "d69fcc38-21a6-41ee-8c0f-90be24aff805"},
{"senado_membership_registration_id": "516", "start_date": "2019-02-01", "finish_data": "2023-01-31", "person_registration_id": "90", "senador_name": "José Serra", "name": "José Serra", "role_resource_uri": "d69fcc38-21a6-41ee-8c0f-90be24aff805"},
{"senado_membership_registration_id": "469", "start_date": "2015-02-01", "finish_data": "2019-01-31", "person_registration_id": "5036", "senador_name": "José de Macedo Ferreira", "name": "José de Macedo Ferreira", "role_resource_uri": "d69fcc38-21a6-41ee-8c0f-90be24aff805"},
{"senado_membership_registration_id": "438", "start_date": "2015-02-01", "finish_data": "2019-01-31", "person_registration_id": "950", "senador_name": "João Alberto Souza", "name": "João Alberto de Souza", "role_resource_uri": "d69fcc38-21a6-41ee-8c0f-90be24aff805"},
{"senado_membership_registration_id": "509", "start_date": "2019-02-01", "finish_data": "2023-01-31", "person_registration_id": "5613", "senador_name": "João Batista Lemos", "name": "João Batista da Rocha Lemos", "role_resource_uri": "d69fcc38-21a6-41ee-8c0f-90be24aff805"},
{"senado_membership_registration_id": "490", "start_date": "2015-02-01", "finish_data": "2019-01-31", "person_registration_id": "3394", "senador_name": "João Capiberibe", "name": "João Alberto Rodrigues Capiberibe", "role_resource_uri": "d69fcc38-21a6-41ee-8c0f-90be24aff805"},
{"senado_membership_registration_id": "458", "start_date": "2015-02-01", "finish_data": "2019-01-31", "person_registration_id": "5186", "senador_name": "João Claudino Fernandes", "name": "João Claudino Fernandes", "role_resource_uri": "d69fcc38-21a6-41ee-8c0f-90be24aff805"},
{"senado_membership_registration_id": "451", "start_date": "2015-02-01", "finish_data": "2019-01-31", "person_registration_id": "5166", "senador_name": "João Costa", "name": "João Costa Ribeiro Filho", "role_resource_uri": "d69fcc38-21a6-41ee-8c0f-90be24aff805"},
{"senado_membership_registration_id": "481", "start_date": "2015-02-01", "finish_data": "2019-01-31", "person_registration_id": "3593", "senador_name": "João Faustino", "name": "João Faustino Ferreira Neto", "role_resource_uri": "d69fcc38-21a6-41ee-8c0f-90be24aff805"},
{"senado_membership_registration_id": "468", "start_date": "2015-02-01", "finish_data": "2019-01-31", "person_registration_id": "916", "senador_name": "João Ribeiro", "name": "João Batista de Jesus Ribeiro", "role_resource_uri": "d69fcc38-21a6-41ee-8c0f-90be24aff805"},
{"senado_membership_registration_id": "461", "start_date": "2015-02-01", "finish_data": "2019-01-31", "person_registration_id": "5066", "senador_name": "Juçara Feitosa de Oliveira", "name": "Juçara Feitosa de Oliveira", "role_resource_uri": "d69fcc38-21a6-41ee-8c0f-90be24aff805"},
{"senado_membership_registration_id": "478", "start_date": "2015-02-01", "finish_data": "2019-01-31", "person_registration_id": "5158", "senador_name": "Kaká Andrade", "name": "Antonio Carlos Porto de Andrade", "role_resource_uri": "d69fcc38-21a6-41ee-8c0f-90be24aff805"},
{"senado_membership_registration_id": "518", "start_date": "2019-02-01", "finish_data": "2023-01-31", "person_registration_id": "1249", "senador_name": "Kátia Abreu", "name": "Kátia Regina de Abreu", "role_resource_uri": "d69fcc38-21a6-41ee-8c0f-90be24aff805"},
{"senado_membership_registration_id": "495", "start_date": "2019-02-01", "finish_data": "2023-01-31", "person_registration_id": "415", "senador_name": "Lael Varella", "name": "Lael Vieira Varella", "role_resource_uri": "d69fcc38-21a6-41ee-8c0f-90be24aff805"},
{"senado_membership_registration_id": "497", "start_date": "2019-02-01", "finish_data": "2023-01-31", "person_registration_id": "5533", "senador_name": "Lasier Martins", "name": "Lasier Costa Martins", "role_resource_uri": "d69fcc38-21a6-41ee-8c0f-90be24aff805"},
{"senado_membership_registration_id": "478", "start_date": "2015-02-01", "finish_data": "2019-01-31", "person_registration_id": "5156", "senador_name": "Lauro Antonio", "name": "Lauro Antonio Texeira Menezes", "role_resource_uri": "d69fcc38-21a6-41ee-8c0f-90be24aff805"},
{"senado_membership_registration_id": "436", "start_date": "2015-02-01", "finish_data": "2019-01-31", "person_registration_id": "3695", "senador_name": "Lindbergh Farias", "name": "Luiz Lindbergh Farias Filho", "role_resource_uri": "d69fcc38-21a6-41ee-8c0f-90be24aff805"},
{"senado_membership_registration_id": "473", "start_date": "2015-02-01", "finish_data": "2019-01-31", "person_registration_id": "5040", "senador_name": "Lirio Albino Parisotto", "name": "Lirio Albino Parisotto", "role_resource_uri": "d69fcc38-21a6-41ee-8c0f-90be24aff805"},
{"senado_membership_registration_id": "445", "start_date": "2015-02-01", "finish_data": "2019-01-31", "person_registration_id": "3579", "senador_name": "Lobão Filho", "name": "Edison Lobão Filho", "role_resource_uri": "d69fcc38-21a6-41ee-8c0f-90be24aff805"},
{"senado_membership_registration_id": "444", "start_date": "2015-02-01", "finish_data": "2019-01-31", "person_registration_id": "5092", "senador_name": "Luis Carlos Paes de Castro", "name": "Luis Carlos Paes de Castro", "role_resource_uri": "d69fcc38-21a6-41ee-8c0f-90be24aff805"},
{"senado_membership_registration_id": "470", "start_date": "2015-02-01", "finish_data": "2019-01-31", "person_registration_id": "5104", "senador_name": "Luis Cláudio da Costa Avelar", "name": "Luis Cláudio da Costa Avelar", "role_resource_uri": "d69fcc38-21a6-41ee-8c0f-90be24aff805"},
{"senado_membership_registration_id": "493", "start_date": "2019-02-01", "finish_data": "2023-01-31", "person_registration_id": "5567", "senador_name": "Luis Mitoso", "name": "Luis Augusto Mitoso Junior", "role_resource_uri": "d69fcc38-21a6-41ee-8c0f-90be24aff805"},
{"senado_membership_registration_id": "504", "start_date": "2019-02-01", "finish_data": "2023-01-31", "person_registration_id": "5585", "senador_name": "Luiz Carlos do Carmo", "name": "Luiz Carlos do Carmo", "role_resource_uri": "d69fcc38-21a6-41ee-8c0f-90be24aff805"},
{"senado_membership_registration_id": "465", "start_date": "2015-02-01", "finish_data": "2019-01-31", "person_registration_id": "5002", "senador_name": "Luiz Henrique", "name": "Luiz Henrique da Silveira", "role_resource_uri": "d69fcc38-21a6-41ee-8c0f-90be24aff805"},
{"senado_membership_registration_id": "503", "start_date": "2019-02-01", "finish_data": "2023-01-31", "person_registration_id": "151", "senador_name": "Luiz Pastore", "name": "Luiz Osvaldo Pastore", "role_resource_uri": "d69fcc38-21a6-41ee-8c0f-90be24aff805"},
{"senado_membership_registration_id": "467", "start_date": "2015-02-01", "finish_data": "2019-01-31", "person_registration_id": "5058", "senador_name": "Luís Guilherme Gomes Mussi", "name": "Luís Guilherme Gomes Mussi", "role_resource_uri": "d69fcc38-21a6-41ee-8c0f-90be24aff805"},
{"senado_membership_registration_id": "461", "start_date": "2015-02-01", "finish_data": "2019-01-31", "person_registration_id": "4575", "senador_name": "Lídice da Mata", "name": "Lídice da Mata e Souza", "role_resource_uri": "d69fcc38-21a6-41ee-8c0f-90be24aff805"},
{"senado_membership_registration_id": "459", "start_date": "2015-02-01", "finish_data": "2019-01-31", "person_registration_id": "643", "senador_name": "Lúcia Vânia", "name": "Lúcia Vânia Abrão", "role_resource_uri": "d69fcc38-21a6-41ee-8c0f-90be24aff805"},
{"senado_membership_registration_id": "483", "start_date": "2015-02-01", "finish_data": "2019-01-31", "person_registration_id": "631", "senador_name": "Magno Malta", "name": "Magno Pereira Malta", "role_resource_uri": "d69fcc38-21a6-41ee-8c0f-90be24aff805"},
{"senado_membership_registration_id": "500", "start_date": "2019-02-01", "finish_data": "2023-01-31", "person_registration_id": "5557", "senador_name": "Mailza Gomes", "name": "Mailza Assis da Silva", "role_resource_uri": "d69fcc38-21a6-41ee-8c0f-90be24aff805"},
{"senado_membership_registration_id": "453", "start_date": "2015-02-01", "finish_data": "2019-01-31", "person_registration_id": "4951", "senador_name": "Manoel Angelo Chagas", "name": "Manoel Angelo Chagas", "role_resource_uri": "d69fcc38-21a6-41ee-8c0f-90be24aff805"},
{"senado_membership_registration_id": "456", "start_date": "2015-02-01", "finish_data": "2019-01-31", "person_registration_id": "5110", "senador_name": "Manoel Antônio Rodrigues Palma", "name": "Manoel Antônio Rodrigues Palma", "role_resource_uri": "d69fcc38-21a6-41ee-8c0f-90be24aff805"},
{"senado_membership_registration_id": "506", "start_date": "2019-02-01", "finish_data": "2023-01-31", "person_registration_id": "5591", "senador_name": "Manoel Motta", "name": "Manoel Francisco de Vasconcelos Motta", "role_resource_uri": "d69fcc38-21a6-41ee-8c0f-90be24aff805"},
{"senado_membership_registration_id": "480", "start_date": "2015-02-01", "finish_data": "2019-01-31", "person_registration_id": "3366", "senador_name": "Marcelo Crivella", "name": "Marcelo Bezerra Crivella", "role_resource_uri": "d69fcc38-21a6-41ee-8c0f-90be24aff805"},
{"senado_membership_registration_id": "479", "start_date": "2015-02-01", "finish_data": "2019-01-31", "person_registration_id": "710", "senador_name": "Marcondes Gadelha", "name": "Marcondes Iran Benevides Gadelha", "role_resource_uri": "d69fcc38-21a6-41ee-8c0f-90be24aff805"},
{"senado_membership_registration_id": "446", "start_date": "2015-02-01", "finish_data": "2019-01-31", "person_registration_id": "5124", "senador_name": "Maria Antonieta Amorim dos Santos", "name": "Maria Antonieta Amorim dos Santos", "role_resource_uri": "d69fcc38-21a6-41ee-8c0f-90be24aff805"},
{"senado_membership_registration_id": "459", "start_date": "2015-02-01", "finish_data": "2019-01-31", "person_registration_id": "5190", "senador_name": "Maria Luza de Aquino Machado", "name": "Maria Luza de Aquino Machado", "role_resource_uri": "d69fcc38-21a6-41ee-8c0f-90be24aff805"},
{"senado_membership_registration_id": "448", "start_date": "2015-02-01", "finish_data": "2019-01-31", "person_registration_id": "5174", "senador_name": "Maria de Pompeia Lins Pessoa", "name": "Maria de Pompeia Lins Pessoa", "role_resource_uri": "d69fcc38-21a6-41ee-8c0f-90be24aff805"},
{"senado_membership_registration_id": "517", "start_date": "2019-02-01", "finish_data": "2023-01-31", "person_registration_id": "1023", "senador_name": "Maria do Carmo Alves", "name": "Maria do Carmo do Nascimento Alves", "role_resource_uri": "d69fcc38-21a6-41ee-8c0f-90be24aff805"},
{"senado_membership_registration_id": "482", "start_date": "2015-02-01", "finish_data": "2019-01-31", "person_registration_id": "4998", "senador_name": "Marinor Brito", "name": "Marinor Jorge Brito", "role_resource_uri": "d69fcc38-21a6-41ee-8c0f-90be24aff805"},
{"senado_membership_registration_id": "492", "start_date": "2019-02-01", "finish_data": "2023-01-31", "person_registration_id": "5575", "senador_name": "Marizete", "name": "Marizete Lisboa Fernandes Pereira", "role_resource_uri": "d69fcc38-21a6-41ee-8c0f-90be24aff805"},
{"senado_membership_registration_id": "501", "start_date": "2019-02-01", "finish_data": "2023-01-31", "person_registration_id": "5571", "senador_name": "Marquinho", "name": "Marco Jeovano Soares Ribas", "role_resource_uri": "d69fcc38-21a6-41ee-8c0f-90be24aff805"},
{"senado_membership_registration_id": "485", "start_date": "2015-02-01", "finish_data": "2019-01-31", "person_registration_id": "5142", "senador_name": "Marta Maria Freire da Costa", "name": "Marta Maria Freire da Costa", "role_resource_uri": "d69fcc38-21a6-41ee-8c0f-90be24aff805"},
{"senado_membership_registration_id": "471", "start_date": "2015-02-01", "finish_data": "2019-01-31", "person_registration_id": "5000", "senador_name": "Marta Suplicy", "name": "Marta Teresa Suplicy", "role_resource_uri": "d69fcc38-21a6-41ee-8c0f-90be24aff805"},
{"senado_membership_registration_id": "438", "start_date": "2015-02-01", "finish_data": "2019-01-31", "person_registration_id": "670", "senador_name": "Mauro Fecury", "name": "Mauro de Alencar Fecury", "role_resource_uri": "d69fcc38-21a6-41ee-8c0f-90be24aff805"},
{"senado_membership_registration_id": "450", "start_date": "2015-02-01", "finish_data": "2019-01-31", "person_registration_id": "5086", "senador_name": "Miguel Dias de Souza", "name": "Miguel Dias de Souza", "role_resource_uri": "d69fcc38-21a6-41ee-8c0f-90be24aff805"},
{"senado_membership_registration_id": "494", "start_date": "2019-02-01", "finish_data": "2023-01-31", "person_registration_id": "5595", "senador_name": "Moacir Kohl", "name": "Moacir Kohl", "role_resource_uri": "d69fcc38-21a6-41ee-8c0f-90be24aff805"},
{"senado_membership_registration_id": "462", "start_date": "2015-02-01", "finish_data": "2019-01-31", "person_registration_id": "5094", "senador_name": "Márcio Bergonsi Turra", "name": "Márcio Bergonsi Turra", "role_resource_uri": "d69fcc38-21a6-41ee-8c0f-90be24aff805"},
{"senado_membership_registration_id": "461", "start_date": "2015-02-01", "finish_data": "2019-01-31", "person_registration_id": "5176", "senador_name": "Nestor Duarte Guimarães Neto", "name": "Nestor Duarte Guimarães Neto", "role_resource_uri": "d69fcc38-21a6-41ee-8c0f-90be24aff805"},
{"senado_membership_registration_id": "487", "start_date": "2015-02-01", "finish_data": "2019-01-31", "person_registration_id": "380", "senador_name": "Nicias Ribeiro", "name": "Nicias Lopes Ribeiro", "role_resource_uri": "d69fcc38-21a6-41ee-8c0f-90be24aff805"},
{"senado_membership_registration_id": "513", "start_date": "2019-02-01", "finish_data": "2023-01-31", "person_registration_id": "5281", "senador_name": "Nilda Gondim", "name": "Ozanilda Gondim Vital do Rego", "role_resource_uri": "d69fcc38-21a6-41ee-8c0f-90be24aff805"},
{"senado_membership_registration_id": "484", "start_date": "2015-02-01", "finish_data": "2019-01-31", "person_registration_id": "288", "senador_name": "Nilson Mourão", "name": "Nilson Moura Leite Mourão", "role_resource_uri": "d69fcc38-21a6-41ee-8c0f-90be24aff805"},
{"senado_membership_registration_id": "477", "start_date": "2015-02-01", "finish_data": "2019-01-31", "person_registration_id": "64", "senador_name": "Odacir Soares", "name": "Odacir Soares Rodrigues", "role_resource_uri": "d69fcc38-21a6-41ee-8c0f-90be24aff805"},
{"senado_membership_registration_id": "436", "start_date": "2015-02-01", "finish_data": "2019-01-31", "person_registration_id": "5060", "senador_name": "Olney Ribeiro Botelho", "name": "Olney Ribeiro Botelho", "role_resource_uri": "d69fcc38-21a6-41ee-8c0f-90be24aff805"},
{"senado_membership_registration_id": "493", "start_date": "2019-02-01", "finish_data": "2023-01-31", "person_registration_id": "5525", "senador_name": "Omar Aziz", "name": "Omar José Abdel Aziz", "role_resource_uri": "d69fcc38-21a6-41ee-8c0f-90be24aff805"},
{"senado_membership_registration_id": "492", "start_date": "2019-02-01", "finish_data": "2023-01-31", "person_registration_id": "5523", "senador_name": "Otto Alencar", "name": "Otto Roberto Mendonça de Alencar", "role_resource_uri": "d69fcc38-21a6-41ee-8c0f-90be24aff805"},
{"senado_membership_registration_id": "486", "start_date": "2015-02-01", "finish_data": "2019-01-31", "person_registration_id": "5080", "senador_name": "Pablo Sergio Souza Bezerra", "name": "Pablo Sergio Souza Bezerra", "role_resource_uri": "d69fcc38-21a6-41ee-8c0f-90be24aff805"},
{"senado_membership_registration_id": "468", "start_date": "2015-02-01", "finish_data": "2019-01-31", "person_registration_id": "918", "senador_name": "Pastor Amarildo", "name": "Amarildo Martins da Silva", "role_resource_uri": "d69fcc38-21a6-41ee-8c0f-90be24aff805"},
{"senado_membership_registration_id": "445", "start_date": "2015-02-01", "finish_data": "2019-01-31", "person_registration_id": "5018", "senador_name": "Pastor Bel", "name": "Heber Waldo Silva Costa", "role_resource_uri": "d69fcc38-21a6-41ee-8c0f-90be24aff805"},
{"senado_membership_registration_id": "507", "start_date": "2019-02-01", "finish_data": "2023-01-31", "person_registration_id": "5599", "senador_name": "Pastor Ibanes Taveira", "name": "Ibanes Taveira da Silva", "role_resource_uri": "d69fcc38-21a6-41ee-8c0f-90be24aff805"},
{"senado_membership_registration_id": "515", "start_date": "2019-02-01", "finish_data": "2023-01-31", "person_registration_id": "5617", "senador_name": "Pastor Valadares", "name": "Sebastião Valadares Neto", "role_resource_uri": "d69fcc38-21a6-41ee-8c0f-90be24aff805"},
{"senado_membership_registration_id": "483", "start_date": "2015-02-01", "finish_data": "2019-01-31", "person_registration_id": "5122", "senador_name": "Paulo Antenor de Oliveira", "name": "Paulo Antenor de Oliveira", "role_resource_uri": "d69fcc38-21a6-41ee-8c0f-90be24aff805"},
{"senado_membership_registration_id": "466", "start_date": "2015-02-01", "finish_data": "2019-01-31", "person_registration_id": "3741", "senador_name": "Paulo Bauer", "name": "Paulo Roberto Bauer", "role_resource_uri": "d69fcc38-21a6-41ee-8c0f-90be24aff805"},
{"senado_membership_registration_id": "476", "start_date": "2015-02-01", "finish_data": "2019-01-31", "person_registration_id": "5020", "senador_name": "Paulo Davim", "name": "Paulo Roberto Davim", "role_resource_uri": "d69fcc38-21a6-41ee-8c0f-90be24aff805"},
{"senado_membership_registration_id": "471", "start_date": "2015-02-01", "finish_data": "2019-01-31", "person_registration_id": "5152", "senador_name": "Paulo Frateschi", "name": "Paulo Frateschi", "role_resource_uri": "d69fcc38-21a6-41ee-8c0f-90be24aff805"},
{"senado_membership_registration_id": "499", "start_date": "2019-02-01", "finish_data": "2023-01-31", "person_registration_id": "824", "senador_name": "Paulo Gouvêa", "name": "Paulo José Gouvêa", "role_resource_uri": "d69fcc38-21a6-41ee-8c0f-90be24aff805"},
{"senado_membership_registration_id": "505", "start_date": "2019-02-01", "finish_data": "2023-01-31", "person_registration_id": "5589", "senador_name": "Paulo Matos", "name": "Paulo Henrique Campos Matos", "role_resource_uri": "d69fcc38-21a6-41ee-8c0f-90be24aff805"},
{"senado_membership_registration_id": "449", "start_date": "2015-02-01", "finish_data": "2019-01-31", "person_registration_id": "825", "senador_name": "Paulo Paim", "name": "Paulo Renato Paim", "role_resource_uri": "d69fcc38-21a6-41ee-8c0f-90be24aff805"},
{"senado_membership_registration_id": "463", "start_date": "2015-02-01", "finish_data": "2019-01-31", "person_registration_id": "5114", "senador_name": "Paulo Pereira Fíuza Filho", "name": "Paulo Pereira Fíuza Filho", "role_resource_uri": "d69fcc38-21a6-41ee-8c0f-90be24aff805"},
{"senado_membership_registration_id": "507", "start_date": "2019-02-01", "finish_data": "2023-01-31", "person_registration_id": "374", "senador_name": "Paulo Rocha", "name": "Paulo Roberto Galvão da Rocha", "role_resource_uri": "d69fcc38-21a6-41ee-8c0f-90be24aff805"},
{"senado_membership_registration_id": "447", "start_date": "2015-02-01", "finish_data": "2019-01-31", "person_registration_id": "5116", "senador_name": "Pedro Chaves", "name": "Pedro Chaves dos Santos Filho", "role_resource_uri": "d69fcc38-21a6-41ee-8c0f-90be24aff805"},
{"senado_membership_registration_id": "439", "start_date": "2015-02-01", "finish_data": "2019-01-31", "person_registration_id": "5050", "senador_name": "Pedro Irno Tonelli", "name": "Pedro Irno Tonelli", "role_resource_uri": "d69fcc38-21a6-41ee-8c0f-90be24aff805"},
{"senado_membership_registration_id": "463", "start_date": "2015-02-01", "finish_data": "2019-01-31", "person_registration_id": "5010", "senador_name": "Pedro Taques", "name": "José Pedro Gonçalves Taques", "role_resource_uri": "d69fcc38-21a6-41ee-8c0f-90be24aff805"},
{"senado_membership_registration_id": "505", "start_date": "2019-02-01", "finish_data": "2023-01-31", "person_registration_id": "4606", "senador_name": "Pinto Itamaraty", "name": "José Eleonildo Soares", "role_resource_uri": "d69fcc38-21a6-41ee-8c0f-90be24aff805"},
{"senado_membership_registration_id": "440", "start_date": "2015-02-01", "finish_data": "2019-01-31", "person_registration_id": "2207", "senador_name": "Raimundo Lira", "name": "Raimundo Lira", "role_resource_uri": "d69fcc38-21a6-41ee-8c0f-90be24aff805"},
{"senado_membership_registration_id": "475", "start_date": "2015-02-01", "finish_data": "2019-01-31", "person_registration_id": "5012", "senador_name": "Randolfe Rodrigues", "name": "Randolph Frederich Rodrigues Alves", "role_resource_uri": "d69fcc38-21a6-41ee-8c0f-90be24aff805"},
{"senado_membership_registration_id": "477", "start_date": "2015-02-01", "finish_data": "2019-01-31", "person_registration_id": "5072", "senador_name": "Reditario Cassol", "name": "Reditario Cassol", "role_resource_uri": "d69fcc38-21a6-41ee-8c0f-90be24aff805"},
{"senado_membership_registration_id": "488", "start_date": "2015-02-01", "finish_data": "2019-01-31", "person_registration_id": "5182", "senador_name": "Regina Sousa", "name": "Maria Regina Sousa", "role_resource_uri": "d69fcc38-21a6-41ee-8c0f-90be24aff805"},
{"senado_membership_registration_id": "502", "start_date": "2019-02-01", "finish_data": "2023-01-31", "person_registration_id": "5236", "senador_name": "Reguffe", "name": "José Antônio Machado Reguffe", "role_resource_uri": "d69fcc38-21a6-41ee-8c0f-90be24aff805"},
{"senado_membership_registration_id": "469", "start_date": "2015-02-01", "finish_data": "2019-01-31", "person_registration_id": "70", "senador_name": "Renan Calheiros", "name": "José Renan Vasconcelos Calheiros", "role_resource_uri": "d69fcc38-21a6-41ee-8c0f-90be24aff805"},
{"senado_membership_registration_id": "455", "start_date": "2015-02-01", "finish_data": "2019-01-31", "person_registration_id": "635", "senador_name": "Ricardo Ferraço", "name": "Ricardo de Rezende Ferraço", "role_resource_uri": "d69fcc38-21a6-41ee-8c0f-90be24aff805"},
{"senado_membership_registration_id": "517", "start_date": "2019-02-01", "finish_data": "2023-01-31", "person_registration_id": "5635", "senador_name": "Ricardo Franco", "name": "Ricardo Barreto Franco", "role_resource_uri": "d69fcc38-21a6-41ee-8c0f-90be24aff805"},
{"senado_membership_registration_id": "454", "start_date": "2015-02-01", "finish_data": "2019-01-31", "person_registration_id": "5052", "senador_name": "Roberto Muniz", "name": "Roberto de Oliveira Muniz", "role_resource_uri": "d69fcc38-21a6-41ee-8c0f-90be24aff805"},
{"senado_membership_registration_id": "467", "start_date": "2015-02-01", "finish_data": "2019-01-31", "person_registration_id": "72", "senador_name": "Roberto Requião", "name": "Roberto Requião de Mello e Silva", "role_resource_uri": "d69fcc38-21a6-41ee-8c0f-90be24aff805"},
{"senado_membership_registration_id": "505", "start_date": "2019-02-01", "finish_data": "2023-01-31", "person_registration_id": "677", "senador_name": "Roberto Rocha", "name": "Roberto Coelho Rocha", "role_resource_uri": "d69fcc38-21a6-41ee-8c0f-90be24aff805"},
{"senado_membership_registration_id": "452", "start_date": "2015-02-01", "finish_data": "2019-01-31", "person_registration_id": "5098", "senador_name": "Roberto Wagner Monteiro", "name": "Roberto Wagner Monteiro", "role_resource_uri": "d69fcc38-21a6-41ee-8c0f-90be24aff805"},
{"senado_membership_registration_id": "470", "start_date": "2015-02-01", "finish_data": "2019-01-31", "person_registration_id": "4593", "senador_name": "Rodrigo Rollemberg", "name": "Rodrigo Sobral Rollemberg", "role_resource_uri": "d69fcc38-21a6-41ee-8c0f-90be24aff805"},
{"senado_membership_registration_id": "460", "start_date": "2015-02-01", "finish_data": "2019-01-31", "person_registration_id": "73", "senador_name": "Romero Jucá", "name": "Romero Jucá Filho", "role_resource_uri": "d69fcc38-21a6-41ee-8c0f-90be24aff805"},
{"senado_membership_registration_id": "509", "start_date": "2019-02-01", "finish_data": "2023-01-31", "person_registration_id": "5322", "senador_name": "Romário", "name": "Romario de Souza Faria", "role_resource_uri": "d69fcc38-21a6-41ee-8c0f-90be24aff805"},
{"senado_membership_registration_id": "504", "start_date": "2019-02-01", "finish_data": "2023-01-31", "person_registration_id": "456", "senador_name": "Ronaldo Caiado", "name": "Ronaldo Ramos Caiado", "role_resource_uri": "d69fcc38-21a6-41ee-8c0f-90be24aff805"},
{"senado_membership_registration_id": "513", "start_date": "2019-02-01", "finish_data": "2023-01-31", "person_registration_id": "5601", "senador_name": "Roosevelt Vita", "name": "Roosevelt Vita", "role_resource_uri": "d69fcc38-21a6-41ee-8c0f-90be24aff805"},
{"senado_membership_registration_id": "503", "start_date": "2019-02-01", "finish_data": "2023-01-31", "person_registration_id": "2331", "senador_name": "Rose de Freitas", "name": "Rosilda de Freitas", "role_resource_uri": "d69fcc38-21a6-41ee-8c0f-90be24aff805"},
{"senado_membership_registration_id": "498", "start_date": "2019-02-01", "finish_data": "2023-01-31", "person_registration_id": "5621", "senador_name": "Rudson Leite", "name": "Rudson Leite da Silva", "role_resource_uri": "d69fcc38-21a6-41ee-8c0f-90be24aff805"},
{"senado_membership_registration_id": "464", "start_date": "2015-02-01", "finish_data": "2019-01-31", "person_registration_id": "4847", "senador_name": "Salomão Alcolumbre Júnior", "name": "Salomão Alcolumbre Júnior", "role_resource_uri": "d69fcc38-21a6-41ee-8c0f-90be24aff805"},
{"senado_membership_registration_id": "460", "start_date": "2015-02-01", "finish_data": "2019-01-31", "person_registration_id": "5074", "senador_name": "Sander Fraxe Salomao", "name": "Sander Fraxe Salomao", "role_resource_uri": "d69fcc38-21a6-41ee-8c0f-90be24aff805"},
{"senado_membership_registration_id": "473", "start_date": "2015-02-01", "finish_data": "2019-01-31", "person_registration_id": "5038", "senador_name": "Sandra Braga", "name": "Sandra Backsmann Braga", "role_resource_uri": "d69fcc38-21a6-41ee-8c0f-90be24aff805"},
{"senado_membership_registration_id": "479", "start_date": "2015-02-01", "finish_data": "2019-01-31", "person_registration_id": "5172", "senador_name": "Sanny Japiassú dos Santos", "name": "Sanny Japiassú dos Santos", "role_resource_uri": "d69fcc38-21a6-41ee-8c0f-90be24aff805"},
{"senado_membership_registration_id": "503", "start_date": "2019-02-01", "finish_data": "2023-01-31", "person_registration_id": "5583", "senador_name": "Schariff Moyses", "name": "Schariff Moyses", "role_resource_uri": "d69fcc38-21a6-41ee-8c0f-90be24aff805"},
{"senado_membership_registration_id": "439", "start_date": "2015-02-01", "finish_data": "2019-01-31", "person_registration_id": "5048", "senador_name": "Sergio Souza", "name": "Sergio de Souza", "role_resource_uri": "d69fcc38-21a6-41ee-8c0f-90be24aff805"},
{"senado_membership_registration_id": "514", "start_date": "2019-02-01", "finish_data": "2023-01-31", "person_registration_id": "5611", "senador_name": "Severino Araujo", "name": "Severino Nunes de Araujo", "role_resource_uri": "d69fcc38-21a6-41ee-8c0f-90be24aff805"},
{"senado_membership_registration_id": "511", "start_date": "2019-02-01", "finish_data": "2023-01-31", "person_registration_id": "5563", "senador_name": "Severino Leão", "name": "Severino Barboza Leão", "role_resource_uri": "d69fcc38-21a6-41ee-8c0f-90be24aff805"},
{"senado_membership_registration_id": "454", "start_date": "2015-02-01", "finish_data": "2019-01-31", "person_registration_id": "5056", "senador_name": "Silvia Nascimento Cardoso dos Santos Cerqueira", "name": "Silvia Nascimento Cardoso dos Santos Cerqueira", "role_resource_uri": "d69fcc38-21a6-41ee-8c0f-90be24aff805"},
{"senado_membership_registration_id": "494", "start_date": "2019-02-01", "finish_data": "2023-01-31", "person_registration_id": "5527", "senador_name": "Simone Tebet", "name": "Simone Nassar Tebet", "role_resource_uri": "d69fcc38-21a6-41ee-8c0f-90be24aff805"},
{"senado_membership_registration_id": "444", "start_date": "2015-02-01", "finish_data": "2019-01-31", "person_registration_id": "624", "senador_name": "Sérgio Novais", "name": "Aluísio Sérgio Novais Eleutério", "role_resource_uri": "d69fcc38-21a6-41ee-8c0f-90be24aff805"},
{"senado_membership_registration_id": "442", "start_date": "2015-02-01", "finish_data": "2019-01-31", "person_registration_id": "4560", "senador_name": "Sérgio Petecão", "name": "Sérgio de Oliveira Cunha", "role_resource_uri": "d69fcc38-21a6-41ee-8c0f-90be24aff805"},
{"senado_membership_registration_id": "455", "start_date": "2015-02-01", "finish_data": "2019-01-31", "person_registration_id": "5106", "senador_name": "Sérgio de Castro", "name": "Sérgio Rogério de Castro", "role_resource_uri": "d69fcc38-21a6-41ee-8c0f-90be24aff805"},
{"senado_membership_registration_id": "512", "start_date": "2019-02-01", "finish_data": "2023-01-31", "person_registration_id": "3396", "senador_name": "Tasso Jereissati", "name": "Tasso Ribeiro Jereissati", "role_resource_uri": "d69fcc38-21a6-41ee-8c0f-90be24aff805"},
{"senado_membership_registration_id": "498", "start_date": "2019-02-01", "finish_data": "2023-01-31", "person_registration_id": "5535", "senador_name": "Telmário Mota", "name": "Telmário Mota de Oliveira", "role_resource_uri": "d69fcc38-21a6-41ee-8c0f-90be24aff805"},
{"senado_membership_registration_id": "510", "start_date": "2019-02-01", "finish_data": "2023-01-31", "person_registration_id": "5629", "senador_name": "Theodorico Netto", "name": "Theodorico Bezerra Netto", "role_resource_uri": "d69fcc38-21a6-41ee-8c0f-90be24aff805"},
{"senado_membership_registration_id": "498", "start_date": "2019-02-01", "finish_data": "2023-01-31", "person_registration_id": "5619", "senador_name": "Thieres Pinto", "name": "Thieres Pinto de Mesquita Filho", "role_resource_uri": "d69fcc38-21a6-41ee-8c0f-90be24aff805"},
{"senado_membership_registration_id": "435", "start_date": "2015-02-01", "finish_data": "2019-01-31", "person_registration_id": "438", "senador_name": "Tilden Santiago", "name": "Tilden José Santiago", "role_resource_uri": "d69fcc38-21a6-41ee-8c0f-90be24aff805"},
{"senado_membership_registration_id": "453", "start_date": "2015-02-01", "finish_data": "2019-01-31", "person_registration_id": "4949", "senador_name": "Tomás Correia", "name": "Tomás Guilherme Correia", "role_resource_uri": "d69fcc38-21a6-41ee-8c0f-90be24aff805"},
{"senado_membership_registration_id": "480", "start_date": "2015-02-01", "finish_data": "2019-01-31", "person_registration_id": "5068", "senador_name": "Tânia Cristina Magalhães Bastos e Silva", "name": "Tânia Cristina Magalhães Bastos e Silva", "role_resource_uri": "d69fcc38-21a6-41ee-8c0f-90be24aff805"},
{"senado_membership_registration_id": "490", "start_date": "2015-02-01", "finish_data": "2019-01-31", "person_registration_id": "5420", "senador_name": "Ubiraci Picanço", "name": "Ubiraci Picanço", "role_resource_uri": "d69fcc38-21a6-41ee-8c0f-90be24aff805"},
{"senado_membership_registration_id": "507", "start_date": "2019-02-01", "finish_data": "2023-01-31", "person_registration_id": "375", "senador_name": "Valdir Ganzer", "name": "Valdir Ganzer", "role_resource_uri": "d69fcc38-21a6-41ee-8c0f-90be24aff805"},
{"senado_membership_registration_id": "453", "start_date": "2015-02-01", "finish_data": "2019-01-31", "person_registration_id": "3372", "senador_name": "Valdir Raupp", "name": "Valdir Raupp de Matos", "role_resource_uri": "d69fcc38-21a6-41ee-8c0f-90be24aff805"},
{"senado_membership_registration_id": "481", "start_date": "2015-02-01", "finish_data": "2019-01-31", "person_registration_id": "5130", "senador_name": "Valério Djalma Cavalcanti Marinho", "name": "Valério Djalma Cavalcanti Marinho", "role_resource_uri": "d69fcc38-21a6-41ee-8c0f-90be24aff805"},
{"senado_membership_registration_id": "437", "start_date": "2015-02-01", "finish_data": "2019-01-31", "person_registration_id": "558", "senador_name": "Vanessa Grazziotin", "name": "Vanessa Grazziotin", "role_resource_uri": "d69fcc38-21a6-41ee-8c0f-90be24aff805"},
{"senado_membership_registration_id": "449", "start_date": "2015-02-01", "finish_data": "2019-01-31", "person_registration_id": "5084", "senador_name": "Veridiana Maria Tonini", "name": "Veridiana Maria Tonini", "role_resource_uri": "d69fcc38-21a6-41ee-8c0f-90be24aff805"},
{"senado_membership_registration_id": "451", "start_date": "2015-02-01", "finish_data": "2019-01-31", "person_registration_id": "4763", "senador_name": "Vicentinho Alves", "name": "Vicente Alves de Oliveira", "role_resource_uri": "d69fcc38-21a6-41ee-8c0f-90be24aff805"},
{"senado_membership_registration_id": "517", "start_date": "2019-02-01", "finish_data": "2023-01-31", "person_registration_id": "4786", "senador_name": "Virginio de Carvalho", "name": "Virginio José de Carvalho Neto", "role_resource_uri": "d69fcc38-21a6-41ee-8c0f-90be24aff805"},
{"senado_membership_registration_id": "440", "start_date": "2015-02-01", "finish_data": "2019-01-31", "person_registration_id": "4645", "senador_name": "Vital do Rêgo", "name": "Vital do Rêgo Filho", "role_resource_uri": "d69fcc38-21a6-41ee-8c0f-90be24aff805"},
{"senado_membership_registration_id": "509", "start_date": "2019-02-01", "finish_data": "2023-01-31", "person_registration_id": "791", "senador_name": "Vivaldo Barbosa", "name": "Vivaldo Vieira Barbosa", "role_resource_uri": "d69fcc38-21a6-41ee-8c0f-90be24aff805"},
{"senado_membership_registration_id": "450", "start_date": "2015-02-01", "finish_data": "2019-01-31", "person_registration_id": "5082", "senador_name": "Waldemir Catanho de Sena Júnior", "name": "Waldemir Catanho de Sena Júnior", "role_resource_uri": "d69fcc38-21a6-41ee-8c0f-90be24aff805"},
{"senado_membership_registration_id": "446", "start_date": "2015-02-01", "finish_data": "2019-01-31", "person_registration_id": "1176", "senador_name": "Waldemir Moka", "name": "Waldemir Moka Miranda de Britto", "role_resource_uri": "d69fcc38-21a6-41ee-8c0f-90be24aff805"},
{"senado_membership_registration_id": "454", "start_date": "2015-02-01", "finish_data": "2019-01-31", "person_registration_id": "604", "senador_name": "Walter Pinheiro", "name": "Walter de Freitas Pinheiro", "role_resource_uri": "d69fcc38-21a6-41ee-8c0f-90be24aff805"},
{"senado_membership_registration_id": "488", "start_date": "2015-02-01", "finish_data": "2019-01-31", "person_registration_id": "5016", "senador_name": "Wellington Dias", "name": "José Wellington Barroso de Araujo Dias", "role_resource_uri": "d69fcc38-21a6-41ee-8c0f-90be24aff805"},
{"senado_membership_registration_id": "506", "start_date": "2019-02-01", "finish_data": "2023-01-31", "person_registration_id": "1173", "senador_name": "Wellington Fagundes", "name": "Wellington Antonio Fagundes", "role_resource_uri": "d69fcc38-21a6-41ee-8c0f-90be24aff805"},
{"senado_membership_registration_id": "472", "start_date": "2015-02-01", "finish_data": "2019-01-31", "person_registration_id": "5070", "senador_name": "Wilder Morais", "name": "Wilder Pedro de Morais", "role_resource_uri": "d69fcc38-21a6-41ee-8c0f-90be24aff805"},
{"senado_membership_registration_id": "452", "start_date": "2015-02-01", "finish_data": "2019-01-31", "person_registration_id": "5096", "senador_name": "Wilmar Lacerda", "name": "Wilmar Lacerda", "role_resource_uri": "d69fcc38-21a6-41ee-8c0f-90be24aff805"},
{"senado_membership_registration_id": "479", "start_date": "2015-02-01", "finish_data": "2019-01-31", "person_registration_id": "3811", "senador_name": "Wilson Santiago", "name": "José Wilson Santiago", "role_resource_uri": "d69fcc38-21a6-41ee-8c0f-90be24aff805"},
{"senado_membership_registration_id": "460", "start_date": "2015-02-01", "finish_data": "2019-01-31", "person_registration_id": "3597", "senador_name": "Wirlande da Luz", "name": "Wirlande Santos da Luz", "role_resource_uri": "d69fcc38-21a6-41ee-8c0f-90be24aff805"},
{"senado_membership_registration_id": "441", "start_date": "2015-02-01", "finish_data": "2019-01-31", "person_registration_id": "5144", "senador_name": "Zeze Perrella", "name": "José Perrella de Oliveira Costa", "role_resource_uri": "d69fcc38-21a6-41ee-8c0f-90be24aff805"},
{"senado_membership_registration_id": "447", "start_date": "2015-02-01", "finish_data": "2019-01-31", "person_registration_id": "5118", "senador_name": "Zonir Freitas Tetila", "name": "Zonir Freitas Tetila", "role_resource_uri": "d69fcc38-21a6-41ee-8c0f-90be24aff805"},
{"senado_membership_registration_id": "486", "start_date": "2015-02-01", "finish_data": "2019-01-31", "person_registration_id": "4697", "senador_name": "Ângela Portela", "name": "Ângela Maria Gomes Portela", "role_resource_uri": "d69fcc38-21a6-41ee-8c0f-90be24aff805"}
]